RPA/__init__.py
RPA/auth.py
RPA/sap_client.py
RPA/sap_keywords.py
rpa_sap_mock_bk-0.1.3.dist-info/licenses/LICENSE
rpa_sap_mock_bk-0.1.3.dist-info/METADATA
rpa_sap_mock_bk-0.1.3.dist-info/WHEEL
rpa_sap_mock_bk-0.1.3.dist-info/top_level.txt
rpa_sap_mock_bk-0.1.3.dist-info/RECORD
