Metadata-Version: 2.4
Name: rpa-sap-mock-bk
Version: 0.1.3
Summary: Robot Framework library for SAP Cloud SDK APIs
Home-page: https://github.com/chiencse/rpa-sap-mock
Author: Minh Chiến
Classifier: Framework :: Robot Framework
Classifier: Programming Language :: Python :: 3
Classifier: License :: OSI Approved :: MIT License
License-File: LICENSE
Requires-Dist: robotframework==6.1.1
Requires-Dist: requests
Requires-Dist: robotframework-pythonlibcore
Dynamic: author
Dynamic: classifier
Dynamic: description
Dynamic: description-content-type
Dynamic: home-page
Dynamic: license-file
Dynamic: requires-dist
Dynamic: summary
